{
    "tutorial": "Creating Your User Profile Tutorial",
    "pageNumber": 6,
    "type": "Tutorial Step - A Mighty Meritocracy",
    "definition": {
        "text": "Superalgos does not reward freeloading! Real contributions to the project and community are what get rewarded with SA tokens and Governance power.",
        "updated": 1629162653518,
        "icon": {
            "name": "Position\\positions",
            "project": "Governance"
        }
    },
    "paragraphs": [
        {
            "style": "Text",
            "text": "The fancy word for this kind of project governance is meritocracy. In other words, the more you contribute to the improvement of Superalgos, and to the support of our community, the more governance power you earn to influence the future of the Superalgos project.",
            "updated": 1629165463461
        },
        {
            "style": "Note",
            "text": "This is a collaboration! Only together can we continue to make Superalgos the game changer it is today no matter what the future may bring.",
            "updated": 1629165548280
        }
    ]
}