{
    "topic": "Pluvtech Data Mine",
    "pageNumber": "14",
    "type": "Donchian-Tenkan",
    "definition": {
        "text": "The Donchian-Tenkan indicator is a short term support/resistance value that can highlight the momentum of an asset. It is a component in the Ichimoku cloud indicators.",
        "updated": 1622696264788,
        "translations": [
            {
                "language": "RU",
                "text": "Индикатор Donchian-Tenkan - это краткосрочное значение поддержки/сопротивления, которое может подчеркнуть импульс актива. Он является компонентом индикаторов облака Ичимоку.",
                "updated": 1645611397047
            },
            {
                "language": "DE",
                "text": "Der Donchian-Tenkan Indikator ist ein kurzfristiger Unterstützungs-/Widerstandswert, der das Momentum eines Vermögenswerts hervorheben kann. Er ist eine Komponente der Ichimoku Cloud Indikatoren.",
                "updated": 1647939120228
            },
            {
                "language": "TR",
                "text": "Donchian-Tenkan göstergesi, bir varlığın momentumunu vurgulayabilen kısa vadeli bir destek/direnç değeridir. Ichimoku bulut göstergelerinin bir bileşenidir.",
                "updated": 1697835921366
            }
        ]
    },
    "paragraphs": [
        {
            "style": "Title",
            "text": "Donchian-Tenkan on the Charts:",
            "updated": 1622481793076,
            "translations": [
                {
                    "language": "RU",
                    "text": "Donchian-Tenkan на графиках:",
                    "updated": 1645611416041
                },
                {
                    "language": "DE",
                    "text": "Donchian-Tenkan in den Charts:",
                    "updated": 1647939151944
                },
                {
                    "language": "TR",
                    "text": "Donchian-Tenkan :",
                    "updated": 1697835942514
                }
            ]
        },
        {
            "style": "Text",
            "text": "The Donchian-Tenkan is calculated by averaging the previous highs and lows to create a donchian channel, and then using the midpoint of these extremes to create the returned value. This value can then be used as a support/resistance line.",
            "translations": [
                {
                    "language": "RU",
                    "text": "Donchian-Tenkan рассчитывается путем усреднения предыдущих максимумов и минимумов для создания канала Donchian, а затем с помощью средней точки этих экстремумов для создания возвращаемого значения. Затем это значение можно использовать в качестве линии поддержки/сопротивления.",
                    "updated": 1645611426437
                },
                {
                    "language": "DE",
                    "text": "Der Donchian-Tenkan wird berechnet, indem der Durchschnitt der vorherigen Höchst- und Tiefstwerte gebildet wird, um einen Donchian-Kanal zu erstellen, und dann der Mittelpunkt dieser Extreme verwendet wird, um den zurückgegebenen Wert zu erstellen. Dieser Wert kann dann als Unterstützungs-/Widerstandslinie verwendet werden.",
                    "updated": 1647939196608
                },
                {
                    "language": "TR",
                    "text": "Donchian-Tenkan, bir donchian kanalı oluşturmak için önceki en yüksek ve en düşük değerlerin ortalaması alınarak ve ardından döndürülen değeri oluşturmak için bu uç noktaların orta noktası kullanılarak hesaplanır. Bu değer daha sonra bir destek/direnç çizgisi olarak kullanılabilir.",
                    "updated": 1697835948289
                }
            ]
        },
        {
            "style": "Png",
            "text": "PNGs/Foundations/Docs/indicators/Pluvtech-Donchian-Tenkan.png",
            "updated": 1611661370646
        },
        {
            "style": "Text",
            "text": "The period length parameter of the Donchian-Tenkan indicator calculation can be changed by locating and opening the Javascript Code under Data Building Procedure -> Procedure Initialization under ’Donchian-Tenkan’ Product Definition.",
            "translations": [
                {
                    "language": "RU",
                    "text": "Параметр длины периода расчета индикатора Donchian-Tenkan можно изменить, найдя и открыв Javascript Code в разделе Data Building Procedure -> Procedure Initialization в разделе 'Donchian-Tenkan' Product Definition.",
                    "updated": 1645611446110
                },
                {
                    "language": "DE",
                    "text": "Der Parameter für die Periodenlänge der Berechnung des Donchian-Tenkan-Indikators kann geändert werden, indem der Javascript Code unter Data Building Procedure -> Procedure Initialization unter ’Donchian-Tenkan’ Product Definition gesucht und geöffnet wird.",
                    "updated": 1647939274755
                },
                {
                    "language": "TR",
                    "text": "Donchian-Tenkan gösterge hesaplamasının dönem uzunluğu parametresi, 'Donchian-Tenkan' Ürün Tanımı altında Veri Oluşturma Prosedürü ( Data Building Procedure ) -> Prosedür Başlatma ( Procedure Initialization ) altındaki Javascript Kodu bulunup açılarak değiştirilebilir.",
                    "updated": 1697835994842
                }
            ]
        },
        {
            "style": "Png",
            "text": "PNGs/Foundations/Docs/indicators/Pluvtech-Donchian-Tenkan-params.png",
            "updated": 1611673329568
        },
        {
            "style": "Title",
            "text": "Products & Properties",
            "translations": [
                {
                    "language": "RU",
                    "text": "Продукты и свойства",
                    "updated": 1645611451571
                },
                {
                    "language": "DE",
                    "text": "Produkte und Eigenschaften",
                    "updated": 1647939309404
                },
                {
                    "language": "TR",
                    "text": "Ürünler & Özellikler",
                    "updated": 1697835999937
                }
            ]
        },
        {
            "style": "Text",
            "text": "The following properties are available to access:",
            "translations": [
                {
                    "language": "RU",
                    "text": "Доступны следующие свойства:",
                    "updated": 1645611457471
                },
                {
                    "language": "DE",
                    "text": "Die folgenden Eigenschaften sind für den Zugriff verfügbar:",
                    "updated": 1647939319924
                },
                {
                    "language": "TR",
                    "text": "Aşağıdaki özelliklere erişilebilir:",
                    "updated": 1697836004113
                }
            ]
        },
        {
            "style": "Table",
            "text": "| Product Name | Product Variable | Properties |\n| Donchian-Tenkan | donchianTenkan | midPoint, closePrice |",
            "updated": 1636853769,
            "translations": [
                {
                    "language": "DE",
                    "text": "| Produktname | Produktvariable | Eigenschaften |\n| Donchian-Tenkan | donchianTenkan | midPoint, closePrice |",
                    "updated": 1647939350157
                }
            ]
        },
        {
            "style": "Text",
            "text": "Examples:",
            "updated": 1611661674316,
            "translations": [
                {
                    "language": "RU",
                    "text": "Примеры:",
                    "updated": 1645611462785
                },
                {
                    "language": "DE",
                    "text": "Beispiele:",
                    "updated": 1647939401847
                },
                {
                    "language": "TR",
                    "text": "Örnekler:",
                    "updated": 1697836007593
                }
            ]
        },
        {
            "style": "Text",
            "text": "The Donchian-Tenkan indicator could be used to generate a buy signal when the close price is above the midPoint value:",
            "translations": [
                {
                    "language": "RU",
                    "text": "Индикатор Donchian-Tenkan может быть использован для генерирования сигнала на покупку, когда цена закрытия находится выше значения средней точки:",
                    "updated": 1645611472537
                },
                {
                    "language": "DE",
                    "text": "Der Donchian-Tenkan-Indikator könnte verwendet werden, um ein Kaufsignal zu erzeugen, wenn der Schlusskurs über dem midPoint Wert liegt:",
                    "updated": 1647939413121
                },
                {
                    "language": "TR",
                    "text": "Donchian-Tenkan göstergesi, kapanış fiyatı orta Nokta değerinin üzerinde olduğunda bir satın alma sinyali oluşturmak için kullanılabilir:",
                    "updated": 1697836012703
                }
            ]
        },
        {
            "style": "Javascript",
            "text": "chart.at01hs.candle.close > chart.at01hs.donchianTenkan.midPoint",
            "updated": 1636853769
        },
        {
            "style": "Text",
            "text": "This indicator could also be used to provide a trailing stop loss when in a trade by checking if the candle close is still above the midPoint value.",
            "translations": [
                {
                    "language": "RU",
                    "text": "Этот индикатор также можно использовать для установки трейлинг-стоп лосса при заключении сделки, проверяя, находится ли закрытие свечи все еще выше значения midPoint.",
                    "updated": 1645611480870
                },
                {
                    "language": "DE",
                    "text": "Dieser Indikator kann auch dazu verwendet werden, einen Trailing-Stop-Loss zu setzen, indem überprüft wird, ob der Kerzenschluss noch über dem midPoint Wert liegt.",
                    "updated": 1647939470294
                },
                {
                    "language": "TR",
                    "text": "Bu gösterge, mum kapanışının hala orta Nokta değerinin üzerinde olup olmadığını kontrol ederek bir işlem sırasında takip eden bir durdurma kaybı sağlamak için de kullanılabilir.",
                    "updated": 1697836028568
                }
            ]
        },
        {
            "style": "Title",
            "text": "Maintainer:",
            "updated": 1622481793076,
            "translations": [
                {
                    "language": "DE",
                    "text": "Betreuer:",
                    "updated": 1647939508214
                }
            ]
        },
        {
            "style": "Link",
            "text": "@pluvtech (Telegram)->t.me/pluvtech"
        }
    ]
}