[
['2021-10-14T19:36:43.355Z',1,'Process Execution Events','[INFO] initialize -> Multi-Time-Frame-Market-Process Definition-9f683143-a33f-42c1-9fa8-c601f01ee4e1-bybit-BTC/USDT based on the Data Mine depends on Historic-OHLCVs']
['2021-10-14T19:36:43.355Z',2,'Process Execution Events','[INFO] initialize -> Connecting to Websockets Server My Computer  -> host = localhost -> port = 18041.']
['2021-10-14T19:36:43.360Z',3,'Process Execution Events','[INFO] start -> waitForDependantProcess -> subscriptionId = undefined']
['2021-10-14T19:36:43.364Z',4,'Process Execution Events','[INFO] initialize -> Connected to Websockets Server My Computer  -> host = localhost -> port = 18041.']
['2021-10-14T19:36:43.364Z',5,'Single Market Indicator Bot','[INFO] run -> loop -> initializeProcessExecutionEvents -> onInizialized -> Execution finished well.']
['2021-10-14T19:36:43.364Z',6,'Process Execution Events','[INFO] start -> waitForDependantProcess -> Entering Code Block.']
['2021-10-14T19:36:43.364Z',7,'Process Execution Events','[INFO] start -> waitForDependantProcess -> started listening to Process Execution Finished. ']
['2021-10-14T19:36:43.364Z',8,'Process Execution Events','[INFO] start -> waitForDependantProcess -> key = Historic-OHLCVs-Process Definition-5eb11d6a-022e-4f60-97c4-d6cf90b249dc-bybit-BTC/USDT']
['2021-10-14T19:36:43.364Z',9,'Process Execution Events','[INFO] start -> waitForDependantProcess -> callerId = Candles-Candles-Volumes-Multi-Time-Frame-Market-2351-']
['2021-10-14T19:36:43.364Z',10,'Process Execution Events','[INFO] start -> waitForDependantProcess -> subscriptionId = 651676']
['2021-10-14T19:37:45.471Z',11,'Process Execution Events','[INFO] start -> eventsCallBack -> Entering function.']
['2021-10-14T19:37:45.471Z',12,'Process Execution Events','[INFO] start -> eventsCallBack -> message = {"action":"Event Raised","eventHandlerName":"Historic-OHLCVs-Process Definition-5eb11d6a-022e-4f60-97c4-d6cf90b249dc-bybit-BTC/USDT","eventType":"Process Execution Finished","event":{"err":{"result":"Ok","message":"Operation Succeeded"}},"callerId":"Candles-Candles-Volumes-Multi-Time-Frame-Market-2351-"}']
['2021-10-14T19:37:45.471Z',13,'Process Execution Events','[INFO] start -> eventsCallBack -> stopListening to Process Execution Finished. ']
['2021-10-14T19:37:45.471Z',14,'Process Execution Events','[INFO] start -> eventsCallBack -> subscriptionId = 651676']
['2021-10-14T19:37:45.471Z',15,'Process Execution Events','[INFO] start -> eventsCallBack -> Multi-Time-Frame-Market-Process Definition-9f683143-a33f-42c1-9fa8-c601f01ee4e1-bybit-BTC/USDT Process Execution Started because Historic-OHLCVs-Process Definition-5eb11d6a-022e-4f60-97c4-d6cf90b249dc-bybit-BTC/USDT Finished.']
['2021-10-14T19:37:45.471Z',16,'Single Market Indicator Bot','[INFO] run -> loop -> startProcessExecutionEvents -> onStarted -> Execution finished well.']
['2021-10-14T19:37:45.472Z',17,'Status Report','[INFO] initialize -> Retrieving status report from My Computer -> host = localhost -> port = 34248.']
['2021-10-14T19:37:45.472Z',18,'Status Dependencies','[INFO] initialize -> onInitilized -> Loading Status Report # 1']
['2021-10-14T19:37:45.472Z',19,'FileStorage','[INFO] FileStorage -> getTextFile -> fileLocation: C:\Users\User\c\superalgos\Platform\My-Data-Storage/Project/Data-Mining/Data-Mine/Candles/Exchange-Raw-Data/bybit/BTC-USDT/Reports/Historic-OHLCVs/Status.Report.json']
['2021-10-14T19:37:45.472Z',20,'Status Report','[INFO] initialize -> Retrieving status report from My Computer -> host = localhost -> port = 34248.']
['2021-10-14T19:37:45.472Z',21,'Status Dependencies','[INFO] initialize -> onInitilized -> Loading Status Report # 2']
['2021-10-14T19:37:45.472Z',22,'FileStorage','[INFO] FileStorage -> getTextFile -> fileLocation: C:\Users\User\c\superalgos\Platform\My-Data-Storage/Project/Data-Mining/Data-Mine/Candles/Exchange-Raw-Data/bybit/BTC-USDT/Reports/Historic-OHLCVs/Status.Report.json']
['2021-10-14T19:37:45.472Z',23,'Status Report','[INFO] initialize -> Retrieving status report from My Computer -> host = localhost -> port = 34248.']
['2021-10-14T19:37:45.472Z',24,'Status Dependencies','[INFO] initialize -> onInitilized -> Loading Status Report # 3']
['2021-10-14T19:37:45.472Z',25,'FileStorage','[INFO] FileStorage -> getTextFile -> fileLocation: C:\Users\User\c\superalgos\Platform\My-Data-Storage/Project/Data-Mining/Data-Mine/Candles/Candles-Volumes/bybit/BTC-USDT/Reports/Multi-Time-Frame-Market/Status.Report.json']
['2021-10-14T19:37:45.473Z',26,'Single Market Indicator Bot','[INFO] run -> loop -> initializeStatusDependencies -> onInizialized -> Execution finished well.']
['2021-10-14T19:37:45.479Z',27,'Dataset','[INFO] initialize -> Retrieving data from My Computer  -> host = localhost -> port = 34248.']
['2021-10-14T19:37:45.482Z',28,'Dataset','[INFO] initialize -> Retrieving data from My Computer  -> host = localhost -> port = 34248.']
['2021-10-14T19:37:45.482Z',29,'Single Market Indicator Bot','[INFO] run -> loop -> initializeBotModuleObject -> onInizialized -> Execution finished well.']
['2021-10-14T19:37:45.483Z',30,'Candles Volumes Multi Time Frame Market','[INFO] start -> findPreviousContent -> loopBody -> timeFrame = 24-hs']
['2021-10-14T19:37:45.483Z',31,'Candles Volumes Multi Time Frame Market','[INFO] start -> findPreviousContent -> loopBody -> getCandles -> getting file.']
['2021-10-14T19:37:45.489Z',32,'Candles Volumes Multi Time Frame Market','[INFO] start -> findPreviousContent -> loopBody -> getVolumes -> getting file.']
['2021-10-14T19:37:45.525Z',33,'Candles Volumes Multi Time Frame Market','[INFO] start -> findPreviousContent -> loopBody -> timeFrame = 12-hs']
['2021-10-14T19:37:45.525Z',34,'Candles Volumes Multi Time Frame Market','[INFO] start -> findPreviousContent -> loopBody -> getCandles -> getting file.']
['2021-10-14T19:37:45.527Z',35,'Candles Volumes Multi Time Frame Market','[INFO] start -> findPreviousContent -> loopBody -> getVolumes -> getting file.']
['2021-10-14T19:37:45.528Z',36,'Candles Volumes Multi Time Frame Market','[INFO] start -> findPreviousContent -> loopBody -> timeFrame = 08-hs']
['2021-10-14T19:37:45.528Z',37,'Candles Volumes Multi Time Frame Market','[INFO] start -> findPreviousContent -> loopBody -> getCandles -> getting file.']
['2021-10-14T19:37:45.531Z',38,'Candles Volumes Multi Time Frame Market','[INFO] start -> findPreviousContent -> loopBody -> getVolumes -> getting file.']
['2021-10-14T19:37:45.535Z',39,'Candles Volumes Multi Time Frame Market','[INFO] start -> findPreviousContent -> loopBody -> timeFrame = 06-hs']
['2021-10-14T19:37:45.535Z',40,'Candles Volumes Multi Time Frame Market','[INFO] start -> findPreviousContent -> loopBody -> getCandles -> getting file.']
['2021-10-14T19:37:45.538Z',41,'Candles Volumes Multi Time Frame Market','[INFO] start -> findPreviousContent -> loopBody -> getVolumes -> getting file.']
['2021-10-14T19:37:45.541Z',42,'Candles Volumes Multi Time Frame Market','[INFO] start -> findPreviousContent -> loopBody -> timeFrame = 04-hs']
['2021-10-14T19:37:45.541Z',43,'Candles Volumes Multi Time Frame Market','[INFO] start -> findPreviousContent -> loopBody -> getCandles -> getting file.']
['2021-10-14T19:37:45.555Z',44,'Candles Volumes Multi Time Frame Market','[INFO] start -> findPreviousContent -> loopBody -> getVolumes -> getting file.']
['2021-10-14T19:37:45.567Z',45,'Candles Volumes Multi Time Frame Market','[INFO] start -> findPreviousContent -> loopBody -> timeFrame = 03-hs']
['2021-10-14T19:37:45.567Z',46,'Candles Volumes Multi Time Frame Market','[INFO] start -> findPreviousContent -> loopBody -> getCandles -> getting file.']
['2021-10-14T19:37:45.573Z',47,'Candles Volumes Multi Time Frame Market','[INFO] start -> findPreviousContent -> loopBody -> getVolumes -> getting file.']
['2021-10-14T19:37:45.582Z',48,'Candles Volumes Multi Time Frame Market','[INFO] start -> findPreviousContent -> loopBody -> timeFrame = 02-hs']
['2021-10-14T19:37:45.582Z',49,'Candles Volumes Multi Time Frame Market','[INFO] start -> findPreviousContent -> loopBody -> getCandles -> getting file.']
['2021-10-14T19:37:45.591Z',50,'Candles Volumes Multi Time Frame Market','[INFO] start -> findPreviousContent -> loopBody -> getVolumes -> getting file.']
['2021-10-14T19:37:45.601Z',51,'Candles Volumes Multi Time Frame Market','[INFO] start -> findPreviousContent -> loopBody -> timeFrame = 01-hs']
['2021-10-14T19:37:45.601Z',52,'Candles Volumes Multi Time Frame Market','[INFO] start -> findPreviousContent -> loopBody -> getCandles -> getting file.']
['2021-10-14T19:37:45.625Z',53,'Candles Volumes Multi Time Frame Market','[INFO] start -> findPreviousContent -> loopBody -> getVolumes -> getting file.']
['2021-10-14T19:37:45.660Z',54,'Candles Volumes Multi Time Frame Market','[INFO] start -> buildCandles -> advanceTime -> New processing time @ 2021/10/14.']
['2021-10-14T19:37:45.661Z',55,'Candles Volumes Multi Time Frame Market','[INFO] start -> buildCandles -> timeframesLoop -> loopBody -> Candle # 568 @ 24-hs discarded for closing past the current process time.']
['2021-10-14T19:37:45.661Z',56,'Candles Volumes Multi Time Frame Market','[INFO] start -> buildCandles -> timeframesLoop -> loopBody -> Volume # 568 @ 24-hs discarded for closing past the current process time.']
['2021-10-14T19:37:45.661Z',57,'Candles Volumes Multi Time Frame Market','[INFO] start -> buildCandles -> timeframesLoop -> loopBody -> nextCandleFile -> getting file at dateForPath = 2021/10/14']
['2021-10-14T19:37:45.663Z',58,'Candles Volumes Multi Time Frame Market','[INFO] start -> buildCandles -> timeframesLoop -> loopBody -> nextVolumeFile -> Entering function.']
['2021-10-14T19:37:45.663Z',59,'Candles Volumes Multi Time Frame Market','[INFO] start -> buildCandles -> timeframesLoop -> loopBody -> nextVolumeFile -> getting file at dateForPath = 2021/10/14']
['2021-10-14T19:37:45.664Z',60,'Candles Volumes Multi Time Frame Market','[INFO] start -> buildCandles -> timeframesLoop -> loopBody -> nextVolumeFile -> onFileReceived -> Entering function.']
['2021-10-14T19:37:45.665Z',61,'Candles Volumes Multi Time Frame Market','[INFO] start -> writeFiles -> Entering function.']
['2021-10-14T19:37:45.665Z',62,'Candles Volumes Multi Time Frame Market','[INFO] start -> writeFiles -> writeCandles -> Entering function.']
['2021-10-14T19:37:45.667Z',63,'Candles Volumes Multi Time Frame Market','[INFO] start -> writeFiles -> writeCandles -> creating file at filePath = Project/Data-Mining/Data-Mine/Candles/Candles-Volumes/bybit/BTC-USDT/Output/Candles/Multi-Time-Frame-Market/24-hs/Data.json']
['2021-10-14T19:37:45.669Z',64,'Candles Volumes Multi Time Frame Market','[INFO] start -> writeFiles -> writeCandles -> onFileCreated -> Entering function.']
['2021-10-14T19:37:45.669Z',65,'Candles Volumes Multi Time Frame Market','[WARN] start -> writeFiles -> writeCandles -> onFileCreated ->  Finished with File @ BTC_USDT, 569 records inserted into Project/Data-Mining/Data-Mine/Candles/Candles-Volumes/bybit/BTC-USDT/Output/Candles/Multi-Time-Frame-Market/24-hs/Data.json/Data.json']
['2021-10-14T19:37:45.676Z',66,'Candles Volumes Multi Time Frame Market','[INFO] start -> writeFiles -> writeVolumes -> creating file at filePath = Project/Data-Mining/Data-Mine/Candles/Candles-Volumes/bybit/BTC-USDT/Output/Volumes/Multi-Time-Frame-Market/24-hs/Data.json']
['2021-10-14T19:37:45.688Z',67,'Candles Volumes Multi Time Frame Market','[WARN] start -> writeFiles -> writeVolumes -> onFileCreated ->  Finished with File @ BTC_USDT, 569 records inserted into Project/Data-Mining/Data-Mine/Candles/Candles-Volumes/bybit/BTC-USDT/Output/Volumes/Multi-Time-Frame-Market/24-hs/Data.json/Data.json']
['2021-10-14T19:37:45.688Z',68,'Candles Volumes Multi Time Frame Market','[INFO] start -> buildCandles -> timeframesLoop -> controlLoop -> Entering function.']
['2021-10-14T19:37:45.689Z',69,'Candles Volumes Multi Time Frame Market','[INFO] start -> buildCandles -> timeframesLoop -> loopBody -> Candle # 1136 @ 12-hs discarded for closing past the current process time.']
['2021-10-14T19:37:45.689Z',70,'Candles Volumes Multi Time Frame Market','[INFO] start -> buildCandles -> timeframesLoop -> loopBody -> Candle # 1137 @ 12-hs discarded for closing past the current process time.']
['2021-10-14T19:37:45.689Z',71,'Candles Volumes Multi Time Frame Market','[INFO] start -> buildCandles -> timeframesLoop -> loopBody -> Volume # 1136 @ 12-hs discarded for closing past the current process time.']
['2021-10-14T19:37:45.689Z',72,'Candles Volumes Multi Time Frame Market','[INFO] start -> buildCandles -> timeframesLoop -> loopBody -> Volume # 1137 @ 12-hs discarded for closing past the current process time.']
['2021-10-14T19:37:45.689Z',73,'Candles Volumes Multi Time Frame Market','[INFO] start -> buildCandles -> timeframesLoop -> loopBody -> nextCandleFile -> getting file at dateForPath = 2021/10/14']
['2021-10-14T19:37:45.691Z',74,'Candles Volumes Multi Time Frame Market','[INFO] start -> buildCandles -> timeframesLoop -> loopBody -> nextVolumeFile -> Entering function.']
['2021-10-14T19:37:45.691Z',75,'Candles Volumes Multi Time Frame Market','[INFO] start -> buildCandles -> timeframesLoop -> loopBody -> nextVolumeFile -> getting file at dateForPath = 2021/10/14']
['2021-10-14T19:37:45.692Z',76,'Candles Volumes Multi Time Frame Market','[INFO] start -> buildCandles -> timeframesLoop -> loopBody -> nextVolumeFile -> onFileReceived -> Entering function.']
['2021-10-14T19:37:45.693Z',77,'Candles Volumes Multi Time Frame Market','[INFO] start -> writeFiles -> Entering function.']
['2021-10-14T19:37:45.693Z',78,'Candles Volumes Multi Time Frame Market','[INFO] start -> writeFiles -> writeCandles -> Entering function.']
['2021-10-14T19:37:45.696Z',79,'Candles Volumes Multi Time Frame Market','[INFO] start -> writeFiles -> writeCandles -> creating file at filePath = Project/Data-Mining/Data-Mine/Candles/Candles-Volumes/bybit/BTC-USDT/Output/Candles/Multi-Time-Frame-Market/12-hs/Data.json']
['2021-10-14T19:37:45.698Z',80,'Candles Volumes Multi Time Frame Market','[INFO] start -> writeFiles -> writeCandles -> onFileCreated -> Entering function.']
['2021-10-14T19:37:45.698Z',81,'Candles Volumes Multi Time Frame Market','[WARN] start -> writeFiles -> writeCandles -> onFileCreated ->  Finished with File @ BTC_USDT, 1138 records inserted into Project/Data-Mining/Data-Mine/Candles/Candles-Volumes/bybit/BTC-USDT/Output/Candles/Multi-Time-Frame-Market/12-hs/Data.json/Data.json']
['2021-10-14T19:37:45.700Z',82,'Candles Volumes Multi Time Frame Market','[INFO] start -> writeFiles -> writeVolumes -> creating file at filePath = Project/Data-Mining/Data-Mine/Candles/Candles-Volumes/bybit/BTC-USDT/Output/Volumes/Multi-Time-Frame-Market/12-hs/Data.json']
['2021-10-14T19:37:45.705Z',83,'Candles Volumes Multi Time Frame Market','[WARN] start -> writeFiles -> writeVolumes -> onFileCreated ->  Finished with File @ BTC_USDT, 1138 records inserted into Project/Data-Mining/Data-Mine/Candles/Candles-Volumes/bybit/BTC-USDT/Output/Volumes/Multi-Time-Frame-Market/12-hs/Data.json/Data.json']
['2021-10-14T19:37:45.705Z',84,'Candles Volumes Multi Time Frame Market','[INFO] start -> buildCandles -> timeframesLoop -> controlLoop -> Entering function.']
['2021-10-14T19:37:45.707Z',85,'Candles Volumes Multi Time Frame Market','[INFO] start -> buildCandles -> timeframesLoop -> loopBody -> Candle # 1704 @ 08-hs discarded for closing past the current process time.']
['2021-10-14T19:37:45.707Z',86,'Candles Volumes Multi Time Frame Market','[INFO] start -> buildCandles -> timeframesLoop -> loopBody -> Candle # 1705 @ 08-hs discarded for closing past the current process time.']
['2021-10-14T19:37:45.707Z',87,'Candles Volumes Multi Time Frame Market','[INFO] start -> buildCandles -> timeframesLoop -> loopBody -> Candle # 1706 @ 08-hs discarded for closing past the current process time.']
['2021-10-14T19:37:45.708Z',88,'Candles Volumes Multi Time Frame Market','[INFO] start -> buildCandles -> timeframesLoop -> loopBody -> Volume # 1704 @ 08-hs discarded for closing past the current process time.']
['2021-10-14T19:37:45.708Z',89,'Candles Volumes Multi Time Frame Market','[INFO] start -> buildCandles -> timeframesLoop -> loopBody -> Volume # 1705 @ 08-hs discarded for closing past the current process time.']
['2021-10-14T19:37:45.708Z',90,'Candles Volumes Multi Time Frame Market','[INFO] start -> buildCandles -> timeframesLoop -> loopBody -> Volume # 1706 @ 08-hs discarded for closing past the current process time.']
['2021-10-14T19:37:45.708Z',91,'Candles Volumes Multi Time Frame Market','[INFO] start -> buildCandles -> timeframesLoop -> loopBody -> nextCandleFile -> getting file at dateForPath = 2021/10/14']
['2021-10-14T19:37:45.712Z',92,'Candles Volumes Multi Time Frame Market','[INFO] start -> buildCandles -> timeframesLoop -> loopBody -> nextVolumeFile -> Entering function.']
['2021-10-14T19:37:45.712Z',93,'Candles Volumes Multi Time Frame Market','[INFO] start -> buildCandles -> timeframesLoop -> loopBody -> nextVolumeFile -> getting file at dateForPath = 2021/10/14']
['2021-10-14T19:37:45.713Z',94,'Candles Volumes Multi Time Frame Market','[INFO] start -> buildCandles -> timeframesLoop -> loopBody -> nextVolumeFile -> onFileReceived -> Entering function.']
['2021-10-14T19:37:45.715Z',95,'Candles Volumes Multi Time Frame Market','[INFO] start -> writeFiles -> Entering function.']
['2021-10-14T19:37:45.716Z',96,'Candles Volumes Multi Time Frame Market','[INFO] start -> writeFiles -> writeCandles -> Entering function.']
['2021-10-14T19:37:45.720Z',97,'Candles Volumes Multi Time Frame Market','[INFO] start -> writeFiles -> writeCandles -> creating file at filePath = Project/Data-Mining/Data-Mine/Candles/Candles-Volumes/bybit/BTC-USDT/Output/Candles/Multi-Time-Frame-Market/08-hs/Data.json']
['2021-10-14T19:37:45.723Z',98,'Candles Volumes Multi Time Frame Market','[INFO] start -> writeFiles -> writeCandles -> onFileCreated -> Entering function.']
['2021-10-14T19:37:45.723Z',99,'Candles Volumes Multi Time Frame Market','[WARN] start -> writeFiles -> writeCandles -> onFileCreated ->  Finished with File @ BTC_USDT, 1707 records inserted into Project/Data-Mining/Data-Mine/Candles/Candles-Volumes/bybit/BTC-USDT/Output/Candles/Multi-Time-Frame-Market/08-hs/Data.json/Data.json']
['2021-10-14T19:37:45.725Z',100,'Candles Volumes Multi Time Frame Market','[INFO] start -> writeFiles -> writeVolumes -> creating file at filePath = Project/Data-Mining/Data-Mine/Candles/Candles-Volumes/bybit/BTC-USDT/Output/Volumes/Multi-Time-Frame-Market/08-hs/Data.json']
['2021-10-14T19:37:45.734Z',101,'Candles Volumes Multi Time Frame Market','[WARN] start -> writeFiles -> writeVolumes -> onFileCreated ->  Finished with File @ BTC_USDT, 1707 records inserted into Project/Data-Mining/Data-Mine/Candles/Candles-Volumes/bybit/BTC-USDT/Output/Volumes/Multi-Time-Frame-Market/08-hs/Data.json/Data.json']
['2021-10-14T19:37:45.734Z',102,'Candles Volumes Multi Time Frame Market','[INFO] start -> buildCandles -> timeframesLoop -> controlLoop -> Entering function.']
['2021-10-14T19:37:45.735Z',103,'Candles Volumes Multi Time Frame Market','[INFO] start -> buildCandles -> timeframesLoop -> loopBody -> Candle # 2272 @ 06-hs discarded for closing past the current process time.']
['2021-10-14T19:37:45.735Z',104,'Candles Volumes Multi Time Frame Market','[INFO] start -> buildCandles -> timeframesLoop -> loopBody -> Candle # 2273 @ 06-hs discarded for closing past the current process time.']
['2021-10-14T19:37:45.735Z',105,'Candles Volumes Multi Time Frame Market','[INFO] start -> buildCandles -> timeframesLoop -> loopBody -> Candle # 2274 @ 06-hs discarded for closing past the current process time.']
['2021-10-14T19:37:45.735Z',106,'Candles Volumes Multi Time Frame Market','[INFO] start -> buildCandles -> timeframesLoop -> loopBody -> Candle # 2275 @ 06-hs discarded for closing past the current process time.']
['2021-10-14T19:37:45.735Z',107,'Candles Volumes Multi Time Frame Market','[INFO] start -> buildCandles -> timeframesLoop -> loopBody -> Volume # 2272 @ 06-hs discarded for closing past the current process time.']
['2021-10-14T19:37:45.735Z',108,'Candles Volumes Multi Time Frame Market','[INFO] start -> buildCandles -> timeframesLoop -> loopBody -> Volume # 2273 @ 06-hs discarded for closing past the current process time.']
['2021-10-14T19:37:45.735Z',109,'Candles Volumes Multi Time Frame Market','[INFO] start -> buildCandles -> timeframesLoop -> loopBody -> Volume # 2274 @ 06-hs discarded for closing past the current process time.']
['2021-10-14T19:37:45.735Z',110,'Candles Volumes Multi Time Frame Market','[INFO] start -> buildCandles -> timeframesLoop -> loopBody -> Volume # 2275 @ 06-hs discarded for closing past the current process time.']
['2021-10-14T19:37:45.735Z',111,'Candles Volumes Multi Time Frame Market','[INFO] start -> buildCandles -> timeframesLoop -> loopBody -> nextCandleFile -> getting file at dateForPath = 2021/10/14']
['2021-10-14T19:37:45.738Z',112,'Candles Volumes Multi Time Frame Market','[INFO] start -> buildCandles -> timeframesLoop -> loopBody -> nextVolumeFile -> Entering function.']
['2021-10-14T19:37:45.738Z',113,'Candles Volumes Multi Time Frame Market','[INFO] start -> buildCandles -> timeframesLoop -> loopBody -> nextVolumeFile -> getting file at dateForPath = 2021/10/14']
['2021-10-14T19:37:45.740Z',114,'Candles Volumes Multi Time Frame Market','[INFO] start -> buildCandles -> timeframesLoop -> loopBody -> nextVolumeFile -> onFileReceived -> Entering function.']
['2021-10-14T19:37:45.742Z',115,'Candles Volumes Multi Time Frame Market','[INFO] start -> writeFiles -> Entering function.']
['2021-10-14T19:37:45.742Z',116,'Candles Volumes Multi Time Frame Market','[INFO] start -> writeFiles -> writeCandles -> Entering function.']
['2021-10-14T19:37:45.746Z',117,'Candles Volumes Multi Time Frame Market','[INFO] start -> writeFiles -> writeCandles -> creating file at filePath = Project/Data-Mining/Data-Mine/Candles/Candles-Volumes/bybit/BTC-USDT/Output/Candles/Multi-Time-Frame-Market/06-hs/Data.json']
['2021-10-14T19:37:45.748Z',118,'Candles Volumes Multi Time Frame Market','[INFO] start -> writeFiles -> writeCandles -> onFileCreated -> Entering function.']
['2021-10-14T19:37:45.748Z',119,'Candles Volumes Multi Time Frame Market','[WARN] start -> writeFiles -> writeCandles -> onFileCreated ->  Finished with File @ BTC_USDT, 2276 records inserted into Project/Data-Mining/Data-Mine/Candles/Candles-Volumes/bybit/BTC-USDT/Output/Candles/Multi-Time-Frame-Market/06-hs/Data.json/Data.json']
['2021-10-14T19:37:45.751Z',120,'Candles Volumes Multi Time Frame Market','[INFO] start -> writeFiles -> writeVolumes -> creating file at filePath = Project/Data-Mining/Data-Mine/Candles/Candles-Volumes/bybit/BTC-USDT/Output/Volumes/Multi-Time-Frame-Market/06-hs/Data.json']
['2021-10-14T19:37:45.757Z',121,'Candles Volumes Multi Time Frame Market','[WARN] start -> writeFiles -> writeVolumes -> onFileCreated ->  Finished with File @ BTC_USDT, 2276 records inserted into Project/Data-Mining/Data-Mine/Candles/Candles-Volumes/bybit/BTC-USDT/Output/Volumes/Multi-Time-Frame-Market/06-hs/Data.json/Data.json']
['2021-10-14T19:37:45.757Z',122,'Candles Volumes Multi Time Frame Market','[INFO] start -> buildCandles -> timeframesLoop -> controlLoop -> Entering function.']
['2021-10-14T19:37:45.757Z',123,'Candles Volumes Multi Time Frame Market','[INFO] start -> buildCandles -> timeframesLoop -> loopBody -> Candle # 3408 @ 04-hs discarded for closing past the current process time.']
['2021-10-14T19:37:45.757Z',124,'Candles Volumes Multi Time Frame Market','[INFO] start -> buildCandles -> timeframesLoop -> loopBody -> Candle # 3409 @ 04-hs discarded for closing past the current process time.']
['2021-10-14T19:37:45.757Z',125,'Candles Volumes Multi Time Frame Market','[INFO] start -> buildCandles -> timeframesLoop -> loopBody -> Candle # 3410 @ 04-hs discarded for closing past the current process time.']
['2021-10-14T19:37:45.757Z',126,'Candles Volumes Multi Time Frame Market','[INFO] start -> buildCandles -> timeframesLoop -> loopBody -> Candle # 3411 @ 04-hs discarded for closing past the current process time.']
['2021-10-14T19:37:45.757Z',127,'Candles Volumes Multi Time Frame Market','[INFO] start -> buildCandles -> timeframesLoop -> loopBody -> Candle # 3412 @ 04-hs discarded for closing past the current process time.']
['2021-10-14T19:37:45.758Z',128,'Candles Volumes Multi Time Frame Market','[INFO] start -> buildCandles -> timeframesLoop -> loopBody -> Volume # 3408 @ 04-hs discarded for closing past the current process time.']
['2021-10-14T19:37:45.758Z',129,'Candles Volumes Multi Time Frame Market','[INFO] start -> buildCandles -> timeframesLoop -> loopBody -> Volume # 3409 @ 04-hs discarded for closing past the current process time.']
['2021-10-14T19:37:45.758Z',130,'Candles Volumes Multi Time Frame Market','[INFO] start -> buildCandles -> timeframesLoop -> loopBody -> Volume # 3410 @ 04-hs discarded for closing past the current process time.']
['2021-10-14T19:37:45.758Z',131,'Candles Volumes Multi Time Frame Market','[INFO] start -> buildCandles -> timeframesLoop -> loopBody -> Volume # 3411 @ 04-hs discarded for closing past the current process time.']
['2021-10-14T19:37:45.758Z',132,'Candles Volumes Multi Time Frame Market','[INFO] start -> buildCandles -> timeframesLoop -> loopBody -> Volume # 3412 @ 04-hs discarded for closing past the current process time.']
['2021-10-14T19:37:45.758Z',133,'Candles Volumes Multi Time Frame Market','[INFO] start -> buildCandles -> timeframesLoop -> loopBody -> nextCandleFile -> getting file at dateForPath = 2021/10/14']
['2021-10-14T19:37:45.759Z',134,'Candles Volumes Multi Time Frame Market','[INFO] start -> buildCandles -> timeframesLoop -> loopBody -> nextVolumeFile -> Entering function.']
['2021-10-14T19:37:45.759Z',135,'Candles Volumes Multi Time Frame Market','[INFO] start -> buildCandles -> timeframesLoop -> loopBody -> nextVolumeFile -> getting file at dateForPath = 2021/10/14']
['2021-10-14T19:37:45.761Z',136,'Candles Volumes Multi Time Frame Market','[INFO] start -> buildCandles -> timeframesLoop -> loopBody -> nextVolumeFile -> onFileReceived -> Entering function.']
['2021-10-14T19:37:45.763Z',137,'Candles Volumes Multi Time Frame Market','[INFO] start -> writeFiles -> Entering function.']
['2021-10-14T19:37:45.764Z',138,'Candles Volumes Multi Time Frame Market','[INFO] start -> writeFiles -> writeCandles -> Entering function.']
['2021-10-14T19:37:45.770Z',139,'Candles Volumes Multi Time Frame Market','[INFO] start -> writeFiles -> writeCandles -> creating file at filePath = Project/Data-Mining/Data-Mine/Candles/Candles-Volumes/bybit/BTC-USDT/Output/Candles/Multi-Time-Frame-Market/04-hs/Data.json']
['2021-10-14T19:37:45.773Z',140,'Candles Volumes Multi Time Frame Market','[INFO] start -> writeFiles -> writeCandles -> onFileCreated -> Entering function.']
['2021-10-14T19:37:45.773Z',141,'Candles Volumes Multi Time Frame Market','[WARN] start -> writeFiles -> writeCandles -> onFileCreated ->  Finished with File @ BTC_USDT, 3413 records inserted into Project/Data-Mining/Data-Mine/Candles/Candles-Volumes/bybit/BTC-USDT/Output/Candles/Multi-Time-Frame-Market/04-hs/Data.json/Data.json']
['2021-10-14T19:37:45.778Z',142,'Candles Volumes Multi Time Frame Market','[INFO] start -> writeFiles -> writeVolumes -> creating file at filePath = Project/Data-Mining/Data-Mine/Candles/Candles-Volumes/bybit/BTC-USDT/Output/Volumes/Multi-Time-Frame-Market/04-hs/Data.json']
['2021-10-14T19:37:45.786Z',143,'Candles Volumes Multi Time Frame Market','[WARN] start -> writeFiles -> writeVolumes -> onFileCreated ->  Finished with File @ BTC_USDT, 3413 records inserted into Project/Data-Mining/Data-Mine/Candles/Candles-Volumes/bybit/BTC-USDT/Output/Volumes/Multi-Time-Frame-Market/04-hs/Data.json/Data.json']
['2021-10-14T19:37:45.786Z',144,'Candles Volumes Multi Time Frame Market','[INFO] start -> buildCandles -> timeframesLoop -> controlLoop -> Entering function.']
['2021-10-14T19:37:45.787Z',145,'Candles Volumes Multi Time Frame Market','[INFO] start -> buildCandles -> timeframesLoop -> loopBody -> Candle # 4544 @ 03-hs discarded for closing past the current process time.']
['2021-10-14T19:37:45.787Z',146,'Candles Volumes Multi Time Frame Market','[INFO] start -> buildCandles -> timeframesLoop -> loopBody -> Candle # 4545 @ 03-hs discarded for closing past the current process time.']
['2021-10-14T19:37:45.787Z',147,'Candles Volumes Multi Time Frame Market','[INFO] start -> buildCandles -> timeframesLoop -> loopBody -> Candle # 4546 @ 03-hs discarded for closing past the current process time.']
['2021-10-14T19:37:45.787Z',148,'Candles Volumes Multi Time Frame Market','[INFO] start -> buildCandles -> timeframesLoop -> loopBody -> Candle # 4547 @ 03-hs discarded for closing past the current process time.']
['2021-10-14T19:37:45.787Z',149,'Candles Volumes Multi Time Frame Market','[INFO] start -> buildCandles -> timeframesLoop -> loopBody -> Candle # 4548 @ 03-hs discarded for closing past the current process time.']
['2021-10-14T19:37:45.787Z',150,'Candles Volumes Multi Time Frame Market','[INFO] start -> buildCandles -> timeframesLoop -> loopBody -> Candle # 4549 @ 03-hs discarded for closing past the current process time.']
['2021-10-14T19:37:45.787Z',151,'Candles Volumes Multi Time Frame Market','[INFO] start -> buildCandles -> timeframesLoop -> loopBody -> Candle # 4550 @ 03-hs discarded for closing past the current process time.']
['2021-10-14T19:37:45.787Z',152,'Candles Volumes Multi Time Frame Market','[INFO] start -> buildCandles -> timeframesLoop -> loopBody -> Volume # 4544 @ 03-hs discarded for closing past the current process time.']
['2021-10-14T19:37:45.787Z',153,'Candles Volumes Multi Time Frame Market','[INFO] start -> buildCandles -> timeframesLoop -> loopBody -> Volume # 4545 @ 03-hs discarded for closing past the current process time.']
['2021-10-14T19:37:45.787Z',154,'Candles Volumes Multi Time Frame Market','[INFO] start -> buildCandles -> timeframesLoop -> loopBody -> Volume # 4546 @ 03-hs discarded for closing past the current process time.']
['2021-10-14T19:37:45.787Z',155,'Candles Volumes Multi Time Frame Market','[INFO] start -> buildCandles -> timeframesLoop -> loopBody -> Volume # 4547 @ 03-hs discarded for closing past the current process time.']
['2021-10-14T19:37:45.787Z',156,'Candles Volumes Multi Time Frame Market','[INFO] start -> buildCandles -> timeframesLoop -> loopBody -> Volume # 4548 @ 03-hs discarded for closing past the current process time.']
['2021-10-14T19:37:45.787Z',157,'Candles Volumes Multi Time Frame Market','[INFO] start -> buildCandles -> timeframesLoop -> loopBody -> Volume # 4549 @ 03-hs discarded for closing past the current process time.']
['2021-10-14T19:37:45.787Z',158,'Candles Volumes Multi Time Frame Market','[INFO] start -> buildCandles -> timeframesLoop -> loopBody -> Volume # 4550 @ 03-hs discarded for closing past the current process time.']
['2021-10-14T19:37:45.787Z',159,'Candles Volumes Multi Time Frame Market','[INFO] start -> buildCandles -> timeframesLoop -> loopBody -> nextCandleFile -> getting file at dateForPath = 2021/10/14']
['2021-10-14T19:37:45.788Z',160,'Candles Volumes Multi Time Frame Market','[INFO] start -> buildCandles -> timeframesLoop -> loopBody -> nextVolumeFile -> Entering function.']
['2021-10-14T19:37:45.788Z',161,'Candles Volumes Multi Time Frame Market','[INFO] start -> buildCandles -> timeframesLoop -> loopBody -> nextVolumeFile -> getting file at dateForPath = 2021/10/14']
['2021-10-14T19:37:45.789Z',162,'Candles Volumes Multi Time Frame Market','[INFO] start -> buildCandles -> timeframesLoop -> loopBody -> nextVolumeFile -> onFileReceived -> Entering function.']
['2021-10-14T19:37:45.790Z',163,'Candles Volumes Multi Time Frame Market','[INFO] start -> writeFiles -> Entering function.']
['2021-10-14T19:37:45.790Z',164,'Candles Volumes Multi Time Frame Market','[INFO] start -> writeFiles -> writeCandles -> Entering function.']
['2021-10-14T19:37:45.795Z',165,'Candles Volumes Multi Time Frame Market','[INFO] start -> writeFiles -> writeCandles -> creating file at filePath = Project/Data-Mining/Data-Mine/Candles/Candles-Volumes/bybit/BTC-USDT/Output/Candles/Multi-Time-Frame-Market/03-hs/Data.json']
['2021-10-14T19:37:45.797Z',166,'Candles Volumes Multi Time Frame Market','[INFO] start -> writeFiles -> writeCandles -> onFileCreated -> Entering function.']
['2021-10-14T19:37:45.797Z',167,'Candles Volumes Multi Time Frame Market','[WARN] start -> writeFiles -> writeCandles -> onFileCreated ->  Finished with File @ BTC_USDT, 4551 records inserted into Project/Data-Mining/Data-Mine/Candles/Candles-Volumes/bybit/BTC-USDT/Output/Candles/Multi-Time-Frame-Market/03-hs/Data.json/Data.json']
['2021-10-14T19:37:45.801Z',168,'Candles Volumes Multi Time Frame Market','[INFO] start -> writeFiles -> writeVolumes -> creating file at filePath = Project/Data-Mining/Data-Mine/Candles/Candles-Volumes/bybit/BTC-USDT/Output/Volumes/Multi-Time-Frame-Market/03-hs/Data.json']
['2021-10-14T19:37:45.809Z',169,'Candles Volumes Multi Time Frame Market','[WARN] start -> writeFiles -> writeVolumes -> onFileCreated ->  Finished with File @ BTC_USDT, 4551 records inserted into Project/Data-Mining/Data-Mine/Candles/Candles-Volumes/bybit/BTC-USDT/Output/Volumes/Multi-Time-Frame-Market/03-hs/Data.json/Data.json']
['2021-10-14T19:37:45.809Z',170,'Candles Volumes Multi Time Frame Market','[INFO] start -> buildCandles -> timeframesLoop -> controlLoop -> Entering function.']
['2021-10-14T19:37:45.810Z',171,'Candles Volumes Multi Time Frame Market','[INFO] start -> buildCandles -> timeframesLoop -> loopBody -> Candle # 6816 @ 02-hs discarded for closing past the current process time.']
['2021-10-14T19:37:45.810Z',172,'Candles Volumes Multi Time Frame Market','[INFO] start -> buildCandles -> timeframesLoop -> loopBody -> Candle # 6817 @ 02-hs discarded for closing past the current process time.']
['2021-10-14T19:37:45.810Z',173,'Candles Volumes Multi Time Frame Market','[INFO] start -> buildCandles -> timeframesLoop -> loopBody -> Candle # 6818 @ 02-hs discarded for closing past the current process time.']
['2021-10-14T19:37:45.810Z',174,'Candles Volumes Multi Time Frame Market','[INFO] start -> buildCandles -> timeframesLoop -> loopBody -> Candle # 6819 @ 02-hs discarded for closing past the current process time.']
['2021-10-14T19:37:45.810Z',175,'Candles Volumes Multi Time Frame Market','[INFO] start -> buildCandles -> timeframesLoop -> loopBody -> Candle # 6820 @ 02-hs discarded for closing past the current process time.']
['2021-10-14T19:37:45.810Z',176,'Candles Volumes Multi Time Frame Market','[INFO] start -> buildCandles -> timeframesLoop -> loopBody -> Candle # 6821 @ 02-hs discarded for closing past the current process time.']
['2021-10-14T19:37:45.810Z',177,'Candles Volumes Multi Time Frame Market','[INFO] start -> buildCandles -> timeframesLoop -> loopBody -> Candle # 6822 @ 02-hs discarded for closing past the current process time.']
['2021-10-14T19:37:45.810Z',178,'Candles Volumes Multi Time Frame Market','[INFO] start -> buildCandles -> timeframesLoop -> loopBody -> Candle # 6823 @ 02-hs discarded for closing past the current process time.']
['2021-10-14T19:37:45.810Z',179,'Candles Volumes Multi Time Frame Market','[INFO] start -> buildCandles -> timeframesLoop -> loopBody -> Candle # 6824 @ 02-hs discarded for closing past the current process time.']
['2021-10-14T19:37:45.810Z',180,'Candles Volumes Multi Time Frame Market','[INFO] start -> buildCandles -> timeframesLoop -> loopBody -> Candle # 6825 @ 02-hs discarded for closing past the current process time.']
['2021-10-14T19:37:45.810Z',181,'Candles Volumes Multi Time Frame Market','[INFO] start -> buildCandles -> timeframesLoop -> loopBody -> Volume # 6816 @ 02-hs discarded for closing past the current process time.']
['2021-10-14T19:37:45.810Z',182,'Candles Volumes Multi Time Frame Market','[INFO] start -> buildCandles -> timeframesLoop -> loopBody -> Volume # 6817 @ 02-hs discarded for closing past the current process time.']
['2021-10-14T19:37:45.810Z',183,'Candles Volumes Multi Time Frame Market','[INFO] start -> buildCandles -> timeframesLoop -> loopBody -> Volume # 6818 @ 02-hs discarded for closing past the current process time.']
['2021-10-14T19:37:45.810Z',184,'Candles Volumes Multi Time Frame Market','[INFO] start -> buildCandles -> timeframesLoop -> loopBody -> Volume # 6819 @ 02-hs discarded for closing past the current process time.']
['2021-10-14T19:37:45.810Z',185,'Candles Volumes Multi Time Frame Market','[INFO] start -> buildCandles -> timeframesLoop -> loopBody -> Volume # 6820 @ 02-hs discarded for closing past the current process time.']
['2021-10-14T19:37:45.810Z',186,'Candles Volumes Multi Time Frame Market','[INFO] start -> buildCandles -> timeframesLoop -> loopBody -> Volume # 6821 @ 02-hs discarded for closing past the current process time.']
['2021-10-14T19:37:45.810Z',187,'Candles Volumes Multi Time Frame Market','[INFO] start -> buildCandles -> timeframesLoop -> loopBody -> Volume # 6822 @ 02-hs discarded for closing past the current process time.']
['2021-10-14T19:37:45.810Z',188,'Candles Volumes Multi Time Frame Market','[INFO] start -> buildCandles -> timeframesLoop -> loopBody -> Volume # 6823 @ 02-hs discarded for closing past the current process time.']
['2021-10-14T19:37:45.810Z',189,'Candles Volumes Multi Time Frame Market','[INFO] start -> buildCandles -> timeframesLoop -> loopBody -> Volume # 6824 @ 02-hs discarded for closing past the current process time.']
['2021-10-14T19:37:45.810Z',190,'Candles Volumes Multi Time Frame Market','[INFO] start -> buildCandles -> timeframesLoop -> loopBody -> Volume # 6825 @ 02-hs discarded for closing past the current process time.']
['2021-10-14T19:37:45.810Z',191,'Candles Volumes Multi Time Frame Market','[INFO] start -> buildCandles -> timeframesLoop -> loopBody -> nextCandleFile -> getting file at dateForPath = 2021/10/14']
['2021-10-14T19:37:45.812Z',192,'Candles Volumes Multi Time Frame Market','[INFO] start -> buildCandles -> timeframesLoop -> loopBody -> nextVolumeFile -> Entering function.']
['2021-10-14T19:37:45.812Z',193,'Candles Volumes Multi Time Frame Market','[INFO] start -> buildCandles -> timeframesLoop -> loopBody -> nextVolumeFile -> getting file at dateForPath = 2021/10/14']
['2021-10-14T19:37:45.813Z',194,'Candles Volumes Multi Time Frame Market','[INFO] start -> buildCandles -> timeframesLoop -> loopBody -> nextVolumeFile -> onFileReceived -> Entering function.']
['2021-10-14T19:37:45.814Z',195,'Candles Volumes Multi Time Frame Market','[INFO] start -> writeFiles -> Entering function.']
['2021-10-14T19:37:45.814Z',196,'Candles Volumes Multi Time Frame Market','[INFO] start -> writeFiles -> writeCandles -> Entering function.']
['2021-10-14T19:37:45.822Z',197,'Candles Volumes Multi Time Frame Market','[INFO] start -> writeFiles -> writeCandles -> creating file at filePath = Project/Data-Mining/Data-Mine/Candles/Candles-Volumes/bybit/BTC-USDT/Output/Candles/Multi-Time-Frame-Market/02-hs/Data.json']
['2021-10-14T19:37:45.826Z',198,'Candles Volumes Multi Time Frame Market','[INFO] start -> writeFiles -> writeCandles -> onFileCreated -> Entering function.']
['2021-10-14T19:37:45.826Z',199,'Candles Volumes Multi Time Frame Market','[WARN] start -> writeFiles -> writeCandles -> onFileCreated ->  Finished with File @ BTC_USDT, 6826 records inserted into Project/Data-Mining/Data-Mine/Candles/Candles-Volumes/bybit/BTC-USDT/Output/Candles/Multi-Time-Frame-Market/02-hs/Data.json/Data.json']
['2021-10-14T19:37:45.832Z',200,'Candles Volumes Multi Time Frame Market','[INFO] start -> writeFiles -> writeVolumes -> creating file at filePath = Project/Data-Mining/Data-Mine/Candles/Candles-Volumes/bybit/BTC-USDT/Output/Volumes/Multi-Time-Frame-Market/02-hs/Data.json']
['2021-10-14T19:37:45.841Z',201,'Candles Volumes Multi Time Frame Market','[WARN] start -> writeFiles -> writeVolumes -> onFileCreated ->  Finished with File @ BTC_USDT, 6826 records inserted into Project/Data-Mining/Data-Mine/Candles/Candles-Volumes/bybit/BTC-USDT/Output/Volumes/Multi-Time-Frame-Market/02-hs/Data.json/Data.json']
['2021-10-14T19:37:45.841Z',202,'Candles Volumes Multi Time Frame Market','[INFO] start -> buildCandles -> timeframesLoop -> controlLoop -> Entering function.']
['2021-10-14T19:37:45.842Z',203,'Candles Volumes Multi Time Frame Market','[INFO] start -> buildCandles -> timeframesLoop -> loopBody -> Candle # 13632 @ 01-hs discarded for closing past the current process time.']
['2021-10-14T19:37:45.842Z',204,'Candles Volumes Multi Time Frame Market','[INFO] start -> buildCandles -> timeframesLoop -> loopBody -> Candle # 13633 @ 01-hs discarded for closing past the current process time.']
['2021-10-14T19:37:45.842Z',205,'Candles Volumes Multi Time Frame Market','[INFO] start -> buildCandles -> timeframesLoop -> loopBody -> Candle # 13634 @ 01-hs discarded for closing past the current process time.']
['2021-10-14T19:37:45.842Z',206,'Candles Volumes Multi Time Frame Market','[INFO] start -> buildCandles -> timeframesLoop -> loopBody -> Candle # 13635 @ 01-hs discarded for closing past the current process time.']
['2021-10-14T19:37:45.842Z',207,'Candles Volumes Multi Time Frame Market','[INFO] start -> buildCandles -> timeframesLoop -> loopBody -> Candle # 13636 @ 01-hs discarded for closing past the current process time.']
['2021-10-14T19:37:45.842Z',208,'Candles Volumes Multi Time Frame Market','[INFO] start -> buildCandles -> timeframesLoop -> loopBody -> Candle # 13637 @ 01-hs discarded for closing past the current process time.']
['2021-10-14T19:37:45.842Z',209,'Candles Volumes Multi Time Frame Market','[INFO] start -> buildCandles -> timeframesLoop -> loopBody -> Candle # 13638 @ 01-hs discarded for closing past the current process time.']
['2021-10-14T19:37:45.842Z',210,'Candles Volumes Multi Time Frame Market','[INFO] start -> buildCandles -> timeframesLoop -> loopBody -> Candle # 13639 @ 01-hs discarded for closing past the current process time.']
['2021-10-14T19:37:45.842Z',211,'Candles Volumes Multi Time Frame Market','[INFO] start -> buildCandles -> timeframesLoop -> loopBody -> Candle # 13640 @ 01-hs discarded for closing past the current process time.']
['2021-10-14T19:37:45.842Z',212,'Candles Volumes Multi Time Frame Market','[INFO] start -> buildCandles -> timeframesLoop -> loopBody -> Candle # 13641 @ 01-hs discarded for closing past the current process time.']
['2021-10-14T19:37:45.842Z',213,'Candles Volumes Multi Time Frame Market','[INFO] start -> buildCandles -> timeframesLoop -> loopBody -> Candle # 13642 @ 01-hs discarded for closing past the current process time.']
['2021-10-14T19:37:45.842Z',214,'Candles Volumes Multi Time Frame Market','[INFO] start -> buildCandles -> timeframesLoop -> loopBody -> Candle # 13643 @ 01-hs discarded for closing past the current process time.']
['2021-10-14T19:37:45.842Z',215,'Candles Volumes Multi Time Frame Market','[INFO] start -> buildCandles -> timeframesLoop -> loopBody -> Candle # 13644 @ 01-hs discarded for closing past the current process time.']
['2021-10-14T19:37:45.842Z',216,'Candles Volumes Multi Time Frame Market','[INFO] start -> buildCandles -> timeframesLoop -> loopBody -> Candle # 13645 @ 01-hs discarded for closing past the current process time.']
['2021-10-14T19:37:45.842Z',217,'Candles Volumes Multi Time Frame Market','[INFO] start -> buildCandles -> timeframesLoop -> loopBody -> Candle # 13646 @ 01-hs discarded for closing past the current process time.']
['2021-10-14T19:37:45.842Z',218,'Candles Volumes Multi Time Frame Market','[INFO] start -> buildCandles -> timeframesLoop -> loopBody -> Candle # 13647 @ 01-hs discarded for closing past the current process time.']
['2021-10-14T19:37:45.842Z',219,'Candles Volumes Multi Time Frame Market','[INFO] start -> buildCandles -> timeframesLoop -> loopBody -> Candle # 13648 @ 01-hs discarded for closing past the current process time.']
['2021-10-14T19:37:45.842Z',220,'Candles Volumes Multi Time Frame Market','[INFO] start -> buildCandles -> timeframesLoop -> loopBody -> Candle # 13649 @ 01-hs discarded for closing past the current process time.']
['2021-10-14T19:37:45.842Z',221,'Candles Volumes Multi Time Frame Market','[INFO] start -> buildCandles -> timeframesLoop -> loopBody -> Candle # 13650 @ 01-hs discarded for closing past the current process time.']
['2021-10-14T19:37:45.842Z',222,'Candles Volumes Multi Time Frame Market','[INFO] start -> buildCandles -> timeframesLoop -> loopBody -> Candle # 13651 @ 01-hs discarded for closing past the current process time.']
['2021-10-14T19:37:45.843Z',223,'Candles Volumes Multi Time Frame Market','[INFO] start -> buildCandles -> timeframesLoop -> loopBody -> Volume # 13632 @ 01-hs discarded for closing past the current process time.']
['2021-10-14T19:37:45.843Z',224,'Candles Volumes Multi Time Frame Market','[INFO] start -> buildCandles -> timeframesLoop -> loopBody -> Volume # 13633 @ 01-hs discarded for closing past the current process time.']
['2021-10-14T19:37:45.843Z',225,'Candles Volumes Multi Time Frame Market','[INFO] start -> buildCandles -> timeframesLoop -> loopBody -> Volume # 13634 @ 01-hs discarded for closing past the current process time.']
['2021-10-14T19:37:45.843Z',226,'Candles Volumes Multi Time Frame Market','[INFO] start -> buildCandles -> timeframesLoop -> loopBody -> Volume # 13635 @ 01-hs discarded for closing past the current process time.']
['2021-10-14T19:37:45.843Z',227,'Candles Volumes Multi Time Frame Market','[INFO] start -> buildCandles -> timeframesLoop -> loopBody -> Volume # 13636 @ 01-hs discarded for closing past the current process time.']
['2021-10-14T19:37:45.843Z',228,'Candles Volumes Multi Time Frame Market','[INFO] start -> buildCandles -> timeframesLoop -> loopBody -> Volume # 13637 @ 01-hs discarded for closing past the current process time.']
['2021-10-14T19:37:45.843Z',229,'Candles Volumes Multi Time Frame Market','[INFO] start -> buildCandles -> timeframesLoop -> loopBody -> Volume # 13638 @ 01-hs discarded for closing past the current process time.']
['2021-10-14T19:37:45.843Z',230,'Candles Volumes Multi Time Frame Market','[INFO] start -> buildCandles -> timeframesLoop -> loopBody -> Volume # 13639 @ 01-hs discarded for closing past the current process time.']
['2021-10-14T19:37:45.843Z',231,'Candles Volumes Multi Time Frame Market','[INFO] start -> buildCandles -> timeframesLoop -> loopBody -> Volume # 13640 @ 01-hs discarded for closing past the current process time.']
['2021-10-14T19:37:45.843Z',232,'Candles Volumes Multi Time Frame Market','[INFO] start -> buildCandles -> timeframesLoop -> loopBody -> Volume # 13641 @ 01-hs discarded for closing past the current process time.']
['2021-10-14T19:37:45.843Z',233,'Candles Volumes Multi Time Frame Market','[INFO] start -> buildCandles -> timeframesLoop -> loopBody -> Volume # 13642 @ 01-hs discarded for closing past the current process time.']
['2021-10-14T19:37:45.843Z',234,'Candles Volumes Multi Time Frame Market','[INFO] start -> buildCandles -> timeframesLoop -> loopBody -> Volume # 13643 @ 01-hs discarded for closing past the current process time.']
['2021-10-14T19:37:45.843Z',235,'Candles Volumes Multi Time Frame Market','[INFO] start -> buildCandles -> timeframesLoop -> loopBody -> Volume # 13644 @ 01-hs discarded for closing past the current process time.']
['2021-10-14T19:37:45.843Z',236,'Candles Volumes Multi Time Frame Market','[INFO] start -> buildCandles -> timeframesLoop -> loopBody -> Volume # 13645 @ 01-hs discarded for closing past the current process time.']
['2021-10-14T19:37:45.843Z',237,'Candles Volumes Multi Time Frame Market','[INFO] start -> buildCandles -> timeframesLoop -> loopBody -> Volume # 13646 @ 01-hs discarded for closing past the current process time.']
['2021-10-14T19:37:45.843Z',238,'Candles Volumes Multi Time Frame Market','[INFO] start -> buildCandles -> timeframesLoop -> loopBody -> Volume # 13647 @ 01-hs discarded for closing past the current process time.']
['2021-10-14T19:37:45.843Z',239,'Candles Volumes Multi Time Frame Market','[INFO] start -> buildCandles -> timeframesLoop -> loopBody -> Volume # 13648 @ 01-hs discarded for closing past the current process time.']
['2021-10-14T19:37:45.843Z',240,'Candles Volumes Multi Time Frame Market','[INFO] start -> buildCandles -> timeframesLoop -> loopBody -> Volume # 13649 @ 01-hs discarded for closing past the current process time.']
['2021-10-14T19:37:45.843Z',241,'Candles Volumes Multi Time Frame Market','[INFO] start -> buildCandles -> timeframesLoop -> loopBody -> Volume # 13650 @ 01-hs discarded for closing past the current process time.']
['2021-10-14T19:37:45.843Z',242,'Candles Volumes Multi Time Frame Market','[INFO] start -> buildCandles -> timeframesLoop -> loopBody -> Volume # 13651 @ 01-hs discarded for closing past the current process time.']
['2021-10-14T19:37:45.843Z',243,'Candles Volumes Multi Time Frame Market','[INFO] start -> buildCandles -> timeframesLoop -> loopBody -> nextCandleFile -> getting file at dateForPath = 2021/10/14']
['2021-10-14T19:37:45.851Z',244,'Candles Volumes Multi Time Frame Market','[INFO] start -> buildCandles -> timeframesLoop -> loopBody -> nextVolumeFile -> Entering function.']
['2021-10-14T19:37:45.851Z',245,'Candles Volumes Multi Time Frame Market','[INFO] start -> buildCandles -> timeframesLoop -> loopBody -> nextVolumeFile -> getting file at dateForPath = 2021/10/14']
['2021-10-14T19:37:45.853Z',246,'Candles Volumes Multi Time Frame Market','[INFO] start -> buildCandles -> timeframesLoop -> loopBody -> nextVolumeFile -> onFileReceived -> Entering function.']
['2021-10-14T19:37:45.855Z',247,'Candles Volumes Multi Time Frame Market','[INFO] start -> writeFiles -> Entering function.']
['2021-10-14T19:37:45.855Z',248,'Candles Volumes Multi Time Frame Market','[INFO] start -> writeFiles -> writeCandles -> Entering function.']
['2021-10-14T19:37:45.874Z',249,'Candles Volumes Multi Time Frame Market','[INFO] start -> writeFiles -> writeCandles -> creating file at filePath = Project/Data-Mining/Data-Mine/Candles/Candles-Volumes/bybit/BTC-USDT/Output/Candles/Multi-Time-Frame-Market/01-hs/Data.json']
['2021-10-14T19:37:45.918Z',250,'Candles Volumes Multi Time Frame Market','[INFO] start -> writeFiles -> writeCandles -> onFileCreated -> Entering function.']
['2021-10-14T19:37:45.918Z',251,'Candles Volumes Multi Time Frame Market','[WARN] start -> writeFiles -> writeCandles -> onFileCreated ->  Finished with File @ BTC_USDT, 13652 records inserted into Project/Data-Mining/Data-Mine/Candles/Candles-Volumes/bybit/BTC-USDT/Output/Candles/Multi-Time-Frame-Market/01-hs/Data.json/Data.json']
['2021-10-14T19:37:45.936Z',252,'Candles Volumes Multi Time Frame Market','[INFO] start -> writeFiles -> writeVolumes -> creating file at filePath = Project/Data-Mining/Data-Mine/Candles/Candles-Volumes/bybit/BTC-USDT/Output/Volumes/Multi-Time-Frame-Market/01-hs/Data.json']
['2021-10-14T19:37:45.940Z',253,'Candles Volumes Multi Time Frame Market','[WARN] start -> writeFiles -> writeVolumes -> onFileCreated ->  Finished with File @ BTC_USDT, 13652 records inserted into Project/Data-Mining/Data-Mine/Candles/Candles-Volumes/bybit/BTC-USDT/Output/Volumes/Multi-Time-Frame-Market/01-hs/Data.json/Data.json']
['2021-10-14T19:37:45.940Z',254,'Candles Volumes Multi Time Frame Market','[INFO] start -> buildCandles -> timeframesLoop -> controlLoop -> Entering function.']
['2021-10-14T19:37:45.940Z',255,'Candles Volumes Multi Time Frame Market','[INFO] start -> writeStatusReport -> lastFileDate = Thu Oct 14 2021 02:00:00 GMT+0200 (South Africa Standard Time)']
['2021-10-14T19:37:45.940Z',256,'FileStorage','[INFO] FileStorage -> createTextFile -> fileLocation: C:\Users\User\c\superalgos\Platform\My-Data-Storage/Project/Data-Mining/Data-Mine/Candles/Candles-Volumes/bybit/BTC-USDT/Reports/Multi-Time-Frame-Market/Status.Report.json']
['2021-10-14T19:37:45.945Z',257,'Candles Volumes Multi Time Frame Market','[INFO] start -> buildCandles -> advanceTime -> New processing time @ 2021/10/15.']
['2021-10-14T19:37:45.945Z',258,'Candles Volumes Multi Time Frame Market','[INFO] start -> buildCandles -> advanceTime -> Head of the market found @ 2021/10/15.']
['2021-10-14T19:37:45.945Z',259,'Single Market Indicator Bot','[INFO] run -> loop -> startBotModuleObject -> onFinished -> Execution finished well.']
['2021-10-14T19:37:45.945Z',260,'Process Execution Events','[INFO] finish -> Entering function.']
['2021-10-14T19:37:45.945Z',261,'Process Execution Events','[INFO] finish -> Multi-Time-Frame-Market-Process Definition-9f683143-a33f-42c1-9fa8-c601f01ee4e1-bybit-BTC/USDT Process Execution Finished ']
['2021-10-14T19:37:45.946Z',262,'Single Market Indicator Bot','[INFO] run -> loop -> finishProcessExecutionEvents -> onFinished -> Execution finished well.']
['2021-10-14T19:37:45.946Z',263,'Single Market Indicator Bot','[INFO] run -> loop -> loopControl -> nextWaitTime = Normal']
['2021-10-14T19:37:45.946Z',264,'Single Market Indicator Bot','[INFO] run -> loop -> loopControl -> Restarting Loop in 0 seconds.']
]