{
    "type": "Close Stage",
    "definition": {
        "text": "The close stage deals with the definitions that make up the logic to close a position, including the target rate and size, and order execution."
    },
    "paragraphs": [
        {
            "style": "Block",
            "text": "Content"
        },
        {
            "style": "Title",
            "text": "Optionality",
            "updated": 1615101975045
        },
        {
            "style": "Note",
            "text": "The Close Stage is optional. That means that if you don't need it you can just delete this node and everything should work just fine. "
        },
        {
            "style": "Text",
            "text": "There are situations where users might want to execute both buy and sell orders from within the Open Stage. In those situations they might want to delete the Manage Stage and the Close Stage so that they don't execute at all. That is possible because both are optional. This is how optionality looks like at the code:",
            "updated": 1615102048658
        },
        {
            "style": "Javascript",
            "text": "/*\nThe system allows the user not to define a close stage, because the close stage is optional.\nHere we are goint to see if that is the case and if it is, we will inmidiatelly consider \nthe close stage as closed.\n*/\nif (tradingSystem.tradingStrategies[tradingEngine.tradingCurrent.strategy.index.value].closeStage === undefined) {\n    changeStageStatus('Close Stage', 'Closed', 'Close Stage Undefined')\n    return\n}",
            "updated": 1615102065680
        },
        {
            "style": "Title",
            "text": "Close Stage Concept"
        },
        {
            "style": "Text",
            "text": "The close stage is opened when either the stop loss or take profit targets are hit. It is also opened after the position is opened if the Manage Stage is undefined."
        },
        {
            "style": "Text",
            "text": "In a way, the close stage is virtually a mirror of the open stage, as the same definitions are required to close a position. There are a few logical differences, though."
        },
        {
            "style": "Text",
            "text": "For example, in the open stage, you probably defined the target size as a function of the capital allocated to the trading system. In the close stage, you will likely want to define the target size as a function of the size filled, that is, the amount of the orders placed that was filled during the open stage."
        },
        {
            "style": "Include",
            "text": "Superalgos->Topic->Why My Stage is not Closing?->The Stage Does Not Close",
            "updated": 1615054694042
        }
    ]
}